Metadata-Version: 1.0
Name: distributions-gl-cs
Version: 1.1
Summary: Gaussian and Binomial distributions
Home-page: UNKNOWN
Author: Gabriel Cantanhede
Author-email: gabriel.lcsilva@hotmail.com
License: UNKNOWN
Platform: UNKNOWN
